aws/__init__.py
aws/api/CloudTrail.py
aws/api/CloudWatch.py
aws/api/CloudWatchLogs.py
aws/api/EC2.py
aws/api/IAM.py
aws/api/KMS.py
aws/api/S3.py
aws/api/SNS.py
aws/api/__init__.py
aws/entity/IAMUser.py
aws/entity/KMSKey.py
aws/entity/LogMetricFilter.py
aws/entity/LogMetricFilterSet.py
aws/entity/MetricAlarm.py
aws/entity/RouteTable.py
aws/entity/S3BucketAcl.py
aws/entity/S3BucketLogging.py
aws/entity/S3BucketPolicy.py
aws/entity/SecurityGroup.py
aws/entity/Subcriber.py
aws/entity/Trail.py
aws/entity/__init__.py
aws/util/SecurityGroupRule.py
aws/util/__init__.py
aws_security_test-0.1.0.dist-info/DESCRIPTION.rst
aws_security_test-0.1.0.dist-info/METADATA
aws_security_test-0.1.0.dist-info/RECORD
aws_security_test-0.1.0.dist-info/WHEEL
aws_security_test-0.1.0.dist-info/entry_points.txt
aws_security_test-0.1.0.dist-info/metadata.json
aws_security_test-0.1.0.dist-info/top_level.txt
aws_security_test-0.1.0.dist-info/zip-safe
tests/__init__.py
tests/iam/IamAudit.py
tests/iam/__init__.py
tests/log/LoggingAudit.py
tests/log/__init__.py
tests/monitoring/MonitoringAudit.py
tests/monitoring/__init__.py
tests/networking/NetworkingAudit.py
tests/networking/__init__.py
third_party_modules/HTMLTestRunner.py
third_party_modules/__init__.py
