Metadata-Version: 2.0
Name: aws-security-test
Version: 0.1.0
Summary: Test automation to determine adherence to pre-defined set of security recommendations
Home-page: https://github.com/mikhailadvani/aws-security-test
Author: Mikhail Advani
Author-email: mikhail.advani@gmail.com
License: Apache
Keywords: aws security test iam networking logging monitoring ec2 vpc
Platform: UNKNOWN
Classifier: Development Status :: 4 - Beta
Classifier: Intended Audience :: Developers
Classifier: Intended Audience :: Information Technology
Classifier: Intended Audience :: System Administrators
Classifier: Topic :: Internet
Classifier: Topic :: Security
Classifier: Topic :: Software Development :: Build Tools
Classifier: Topic :: Software Development :: Testing
Classifier: Topic :: System
Classifier: Topic :: System :: Logging
Classifier: Topic :: System :: Monitoring
Classifier: Topic :: System :: Networking :: Firewalls
Classifier: License :: OSI Approved :: Apache Software License
Classifier: Programming Language :: Python :: 2.7
Requires-Dist: boto3
Requires-Dist: pyyaml
Provides-Extra: dev
Requires-Dist: twine; extra == 'dev'
